pgvector_rag/__init__.py
pgvector_rag/rag.py
pgvector_rag-0.5.0.dist-info/METADATA
pgvector_rag-0.5.0.dist-info/WHEEL
pgvector_rag-0.5.0.dist-info/licenses/LICENSE
pgvector_rag-0.5.0.dist-info/RECORD
