Metadata-Version: 2.4
Name: pgvector-rag
Version: 0.5.0
Summary: A library for interfacing with pg_vector for RAG
Project-URL: Repository, https://github.com/gmr/pgvector-rag.git
Author-email: "Gavin M. Roy" <gavinmroy@gmail.com>
License: BSD 3-Clause License
License-File: LICENSE
Classifier: Development Status :: 3 - Alpha
Classifier: Intended Audience :: Developers
Classifier: License :: OSI Approved :: BSD License
Classifier: Natural Language :: English
Classifier: Programming Language :: Python :: 3.12
Classifier: Programming Language :: Python :: 3.13
Classifier: Topic :: Database
Classifier: Topic :: Scientific/Engineering :: Artificial Intelligence
Requires-Python: >=3.12
Requires-Dist: anthropic
Requires-Dist: markdown-it-py
Requires-Dist: openai
Requires-Dist: psycopg
Requires-Dist: pydantic
Requires-Dist: uuid-utils
Provides-Extra: dev
Requires-Dist: build; extra == 'dev'
Requires-Dist: coverage; extra == 'dev'
Requires-Dist: ruff; extra == 'dev'
